vecsync/__init__.py
vecsync/constants.py
vecsync/settings.py
vecsync/chat/__init__.py
vecsync/chat/formatter.py
vecsync/chat/interface.py
vecsync/chat/clients/__init__.py
vecsync/chat/clients/base.py
vecsync/chat/clients/openai.py
vecsync/cli/__init__.py
vecsync/cli/assistants.py
vecsync/cli/chat.py
vecsync/cli/entry.py
vecsync/cli/settings.py
vecsync/cli/store.py
vecsync/cli/sync.py
vecsync/prompts/default_prompt.txt
vecsync/store/__init__.py
vecsync/store/base.py
vecsync/store/file.py
vecsync/store/openai.py
vecsync/store/zotero.py
vecsync-0.7.0.dist-info/METADATA
vecsync-0.7.0.dist-info/WHEEL
vecsync-0.7.0.dist-info/entry_points.txt
vecsync-0.7.0.dist-info/licenses/LICENSE
vecsync-0.7.0.dist-info/RECORD
