Metadata-Version: 2.4
Name: vecsync
Version: 0.7.0
Summary: A simple command-line utility for synchronizing documents to vector storage for LLM interaction.
Project-URL: Homepage, https://vecsync.io
Project-URL: Repository, https://github.com/jbencina/vecsync
Project-URL: Issues, https://github.com/jbencina/vecsync/issues
Project-URL: Changelog, https://github.com/jbencina/vecsync/blob/main/CHANGELOG.md
Author-email: John Bencina <jbencina@users.noreply.github.com>
License:                     GNU GENERAL PUBLIC LICENSE
License-File: LICENSE
Keywords: chatbot,cli,command-line,documents,embeddings,gradio,information retrieval,llm,pdf,semantic search,sync,vector search,zotero
Classifier: Development Status :: 2 - Pre-Alpha
Classifier: Environment :: Console
Classifier: Intended Audience :: Developers
Classifier: Intended Audience :: Science/Research
Classifier: License :: OSI Approved :: GNU General Public License v3 (GPLv3)
Classifier: Operating System :: MacOS :: MacOS X
Classifier: Operating System :: Microsoft :: Windows
Classifier: Operating System :: OS Independent
Classifier: Operating System :: POSIX :: Linux
Classifier: Programming Language :: Python :: 3
Classifier: Programming Language :: Python :: 3.10
Classifier: Programming Language :: Python :: 3.11
Classifier: Programming Language :: Python :: 3.12
Classifier: Programming Language :: Python :: 3.13
Classifier: Topic :: Scientific/Engineering :: Artificial Intelligence
Classifier: Topic :: Scientific/Engineering :: Information Analysis
Classifier: Topic :: Software Development :: Libraries :: Python Modules
Classifier: Topic :: Utilities
Requires-Python: >=3.10
Requires-Dist: appdirs>=1.4.4
Requires-Dist: click>=8.1.8
Requires-Dist: gradio>=5.27.1
Requires-Dist: openai>=1.76.0
Requires-Dist: pydantic>=2.11.3
Requires-Dist: python-dotenv>=1.1.0
Requires-Dist: termcolor>=3.0.1
Requires-Dist: tqdm>=4.67.1
